README.md
setup.cfg
setup.py
pathtub/__init__.py
pathtub/dll.py
pathtub/pathtools.py
pathtub/powershell.py
pathtub/utils.py
pathtub.egg-info/PKG-INFO
pathtub.egg-info/SOURCES.txt
pathtub.egg-info/dependency_links.txt
pathtub.egg-info/top_level.txt