Metadata-Version: 2.1
Name: pathtub
Version: 1.1.2
Summary: Reading and editing Windows PATH.
Home-page: https://github.com/np-8/pathtub
Author: Niko Pasanen
Author-email: niko@pasanen.me
License: MIT
Keywords: PATH,Windows,winpath,powershell
Platform: UNKNOWN
Classifier: Development Status :: 5 - Production/Stable
Classifier: Intended Audience :: Developers
Classifier: Environment :: Win32 (MS Windows)
Classifier: License :: OSI Approved :: MIT License
Classifier: Operating System :: Microsoft :: Windows :: Windows 10
Classifier: Topic :: System :: Shells
Classifier: Programming Language :: Python :: 3.6
Classifier: Programming Language :: Python :: 3.7
